odoo/addons/cron_inactivity_period/README.rst
odoo/addons/cron_inactivity_period/__init__.py
odoo/addons/cron_inactivity_period/__manifest__.py
odoo/addons/cron_inactivity_period/demo/res_groups.xml
odoo/addons/cron_inactivity_period/i18n/cron_inactivity_period.pot
odoo/addons/cron_inactivity_period/i18n/fr.po
odoo/addons/cron_inactivity_period/models/__init__.py
odoo/addons/cron_inactivity_period/models/ir_cron.py
odoo/addons/cron_inactivity_period/models/ir_cron_inactivity_period.py
odoo/addons/cron_inactivity_period/readme/CONFIGURE.rst
odoo/addons/cron_inactivity_period/readme/CONTRIBUTORS.rst
odoo/addons/cron_inactivity_period/readme/DESCRIPTION.rst
odoo/addons/cron_inactivity_period/readme/ROADMAP.rst
odoo/addons/cron_inactivity_period/security/ir.model.access.csv
odoo/addons/cron_inactivity_period/static/description/icon.png
odoo/addons/cron_inactivity_period/static/description/index.html
odoo/addons/cron_inactivity_period/static/description/ir_cron_form.png
odoo/addons/cron_inactivity_period/tests/__init__.py
odoo/addons/cron_inactivity_period/tests/test_module.py
odoo/addons/cron_inactivity_period/views/ir_cron.xml
odoo12_addon_cron_inactivity_period-12.0.1.0.1.dist-info/METADATA
odoo12_addon_cron_inactivity_period-12.0.1.0.1.dist-info/WHEEL
odoo12_addon_cron_inactivity_period-12.0.1.0.1.dist-info/top_level.txt
odoo12_addon_cron_inactivity_period-12.0.1.0.1.dist-info/RECORD
